ament_clang_tidy/__init__.py
ament_clang_tidy/main.py
ament_clang_tidy-0.14.2.data/data/share/ament_clang_tidy/package.xml
ament_clang_tidy-0.14.2.data/data/share/ament_index/resource_index/packages/ament_clang_tidy
ament_clang_tidy-0.14.2.dist-info/METADATA
ament_clang_tidy-0.14.2.dist-info/WHEEL
ament_clang_tidy-0.14.2.dist-info/entry_points.txt
ament_clang_tidy-0.14.2.dist-info/top_level.txt
ament_clang_tidy-0.14.2.dist-info/RECORD
