Metadata-Version: 2.1
Name: ament-clang-tidy
Version: 0.14.2
Summary: Check C++ code style using clang-tidy.
Home-page: https://github.com/ament/ament_lint
Download-URL: https://github.com/ament/ament_lint/releases
Author: John Shepherd
Author-email: john@openrobotics.org
Maintainer: Michael Jeronimo
Maintainer-email: michael.jeronimo@openrobotics.org
License: Apache License, Version 2.0, BSD
Keywords: ROS
Classifier: Intended Audience :: Developers
Classifier: License :: OSI Approved :: Apache Software License
Classifier: Programming Language :: Python
Classifier: Topic :: Software Development
Requires-Dist: setuptools
Requires-Dist: pyyaml
